{
  "geoData": [
    {
      "type": "FeatureCollection",
      "features": [
        {
          "type": "Feature",
          "properties": {
            "name": "New York City",
            "population": 8398748
          },
          "geometry": {
            "type": "Point",
            "coordinates": [
              -74.0059,
              40.7128
            ]
          }
        },
        {
          "type": "Feature",
          "properties": {
            "name": "Los Angeles",
            "population": 3990456
          },
          "geometry": {
            "type": "Point",
            "coordinates": [
              -118.2437,
              34.0522
            ]
          }
        },
        {
          "type": "Feature",
          "properties": {
            "distance": "3941.5 km"
          },
          "geometry": {
            "coordinates": [
              [
                -73.9389351501344,
                40.809955852082965
              ],
              [
                -117.99075649862561,
                34.077027962083946
              ]
            ],
            "type": "LineString"
          }
        },
        {
          "type": "Feature",
          "properties": {
            "name": "Margaret Island",
            "area": "96 ha",
            "attractions": "Medieval ruins, Japanese Garden, Mini Zoo, Musical Fountain",
            "activities": "swimming, cycling, jogging"
          },
          "geometry": {
            "coordinates": [
              [
                [
                  19.054127991986547,
                  47.5386377464925
                ],
                [
                  19.047924824138306,
                  47.53195961455532
                ],
                [
                  19.04289522858582,
                  47.524941000114325
                ],
                [
                  19.04205696266041,
                  47.52211064793474
                ],
                [
                  19.043398188140884,
                  47.514637784440794
                ],
                [
                  19.045745332732395,
                  47.51871402374343
                ],
                [
                  19.048092477323877,
                  47.52075202464698
                ],
                [
                  19.05094258147045,
                  47.52652593063121
                ],
                [
                  19.053625032431455,
                  47.53229920110928
                ],
                [
                  19.054295645172118,
                  47.53512900354542
                ],
                [
                  19.054127991986547,
                  47.5386377464925
                ]
              ]
            ],
            "type": "Polygon"
          }
        },
        {
          "type": "Feature",
          "properties": {
            "name": "Heroes Square",
            "attractions": "Millenium Monument, Museum of Fine Arts, Hall of Art"
          },
          "geometry": {
            "coordinates": [
              19.0777777567109,
              47.51496013377729
            ],
            "type": "Point"
          }
        },
        {
          "type": "Feature",
          "properties": {
            "name": "Budapest Park",
            "attractions": "concerts, festivals, cultural events"
          },
          "geometry": {
            "coordinates": [
              19.07765633559464,
              47.46764590153384
            ],
            "type": "Point"
          }
        },
        {
          "type": "Feature",
          "properties": {},
          "geometry": {
            "coordinates": [
              [
                [
                  19.028540878366158,
                  47.49592289025671
                ],
                [
                  18.9873756754576,
                  47.49592289025671
                ],
                [
                  18.9873756754576,
                  47.4836567117589
                ],
                [
                  19.028540878366158,
                  47.4836567117589
                ],
                [
                  19.028540878366158,
                  47.49592289025671
                ]
              ]
            ],
            "type": "Polygon"
          }
        },
        {
          "type": "Feature",
          "properties": {},
          "geometry": {
            "type": "Polygon",
            "coordinates": [
              [
                [
                  19.095897467348262,
                  47.54256012558642
                ],
                [
                  19.095026707588776,
                  47.542531245526575
                ],
                [
                  19.094164336576707,
                  47.542444883572756
                ],
                [
                  19.093318662161494,
                  47.5423018717189
                ],
                [
                  19.092497831179912,
                  47.542103587703856
                ],
                [
                  19.091709750900325,
                  47.54185194172542
                ],
                [
                  19.09096201278614,
                  47.5415493580205
                ],
                [
                  19.090261819315927,
                  47.54119875148957
                ],
                [
                  19.08961591456766,
                  47.54080349959179
                ],
                [
                  19.08903051923761,
                  47.54036740978258
                ],
                [
                  19.088511270720886,
                  47.53989468280874
                ],
                [
                  19.088063168831123,
                  47.53938987221588
                ],
                [
                  19.08769052768159,
                  47.53885784045966
                ],
                [
                  19.08739693419,
                  47.53830371204499
                ],
                [
                  19.08718521360451,
                  47.53773282414537
                ],
                [
                  19.087057402380303,
                  47.53715067517947
                ],
                [
                  19.08701472866467,
                  47.5365628718408
                ],
                [
                  19.087057600574774,
                  47.53597507509145
                ],
                [
                  19.08718560237695,
                  47.53539294564029
                ],
                [
                  19.087397498600108,
                  47.53482208943088
                ],
                [
                  19.0876912460394,
                  47.534268003664046
                ],
                [
                  19.088064013530545,
                  47.533736023874404
                ],
                [
                  19.088512209300607,
                  47.53323127256974
                ],
                [
                  19.089031515628527,
                  47.53275860992736
                ],
                [
                  19.089616930479032,
                  47.53232258702063
                ],
                [
                  19.09026281570685,
                  47.531927402025346
                ],
                [
                  19.09096295136587,
                  47.53157685982587
                ],
                [
                  19.091710595599768,
                  47.53127433540916
                ],
                [
                  19.09249854953774,
                  47.53102274139729
                ],
                [
                  19.093319226571623,
                  47.53082450003009
                ],
                [
                  19.094164725349167,
                  47.53068151986644
                ],
                [
                  19.095026905783257,
                  47.53059517742736
                ],
                [
                  19.095897467348262,
                  47.53056630395684
                ],
                [
                  19.096768028913274,
                  47.53059517742736
                ],
                [
                  19.097630209347365,
                  47.53068151986644
                ],
                [
                  19.09847570812491,
                  47.53082450003009
                ],
                [
                  19.09929638515879,
                  47.53102274139729
                ],
                [
                  19.10008433909676,
                  47.53127433540916
                ],
                [
                  19.100831983330657,
                  47.53157685982587
                ],
                [
                  19.101532118989677,
                  47.531927402025346
                ],
                [
                  19.102178004217496,
                  47.53232258702063
                ],
                [
                  19.102763419068005,
                  47.53275860992736
                ],
                [
                  19.103282725395925,
                  47.53323127256974
                ],
                [
                  19.103730921165983,
                  47.533736023874404
                ],
                [
                  19.10410368865713,
                  47.534268003664046
                ],
                [
                  19.10439743609642,
                  47.53482208943088
                ],
                [
                  19.104609332319576,
                  47.53539294564029
                ],
                [
                  19.104737334121754,
                  47.53597507509145
                ],
                [
                  19.104780206031858,
                  47.5365628718408
                ],
                [
                  19.10473753231623,
                  47.53715067517947
                ],
                [
                  19.104609721092018,
                  47.53773282414537
                ],
                [
                  19.104398000506528,
                  47.53830371204499
                ],
                [
                  19.104104407014937,
                  47.53885784045966
                ],
                [
                  19.103731765865408,
                  47.53938987221588
                ],
                [
                  19.103283663975642,
                  47.53989468280874
                ],
                [
                  19.102764415458918,
                  47.54036740978258
                ],
                [
                  19.10217902012887,
                  47.54080349959179
                ],
                [
                  19.1015331153806,
                  47.54119875148957
                ],
                [
                  19.10083292191039,
                  47.5415493580205
                ],
                [
                  19.100085183796203,
                  47.54185194172542
                ],
                [
                  19.099297103516616,
                  47.542103587703856
                ],
                [
                  19.098476272535034,
                  47.5423018717189
                ],
                [
                  19.09763059811982,
                  47.542444883572756
                ],
                [
                  19.096768227107756,
                  47.542531245526575
                ],
                [
                  19.095897467348262,
                  47.54256012558642
                ]
              ]
            ]
          }
        },
        {
          "type": "Feature",
          "geometry": {
            "type": "MultiLineString",
            "coordinates": [
              [
                [
                  20.469570,
                  44.807409
                ],
                [
                  20.552814,
                  44.750862
                ],
                [
                  20.618918,
                  44.719848
                ],
                [
                  20.730896,
                  44.703100
                ],
                [
                  20.880719,
                  44.686323
                ],
                [
                  21.005583,
                  44.663798
                ],
                [
                  21.128979,
                  44.630014
                ],
                [
                  21.214309,
                  44.591221
                ],
                [
                  21.280413,
                  44.548547
                ],
                [
                  21.322727,
                  44.508196
                ],
                [
                  21.377167,
                  44.442401
                ],
                [
                  21.410495,
                  44.368776
                ],
                [
                  21.421402,
                  44.290121
                ],
                [
                  21.409183,
                  44.213562
                ],
                [
                  21.355587,
                  44.123108
                ],
                [
                  21.305456,
                  44.064012
                ],
                [
                  21.207700,
                  44.012972
                ],
                [
                  21.076732,
                  43.961900
                ],
                [
                  20.984802,
                  43.923392
                ],
                [
                  20.916954,
                  43.897350
                ],
                [
                  20.825727,
                  43.869281
                ],
                [
                  20.693273,
                  43.839381
                ],
                [
                  20.583417,
                  43.811691
                ],
                [
                  20.492590,
                  43.780842
                ],
                [
                  20.387907,
                  43.748031
                ]
              ]
            ]
          },
          "properties": {
            "distance": "50km"
          }
        }
      ]
    }
  ]
}